stackformer/__init__.py
stackformer/generate.py
stackformer/trainer.py
stackformer/models/Google.py
stackformer/models/Meta.py
stackformer/models/OpenAI.py
stackformer/models/Transformer.py
stackformer/models/__init__.py
stackformer/modules/Attention.py
stackformer/modules/Feed_forward.py
stackformer/modules/Normalization.py
stackformer/modules/__init__.py
stackformer/modules/mask.py
stackformer/modules/position_embedding.py
stackformer/modules/tokenizer.py
stackformer/vision_models/vit.py
stackformer-0.1.6.dist-info/licenses/LICENSE
stackformer-0.1.6.dist-info/METADATA
stackformer-0.1.6.dist-info/WHEEL
stackformer-0.1.6.dist-info/top_level.txt
stackformer-0.1.6.dist-info/RECORD
