Metadata-Version: 2.4
Name: Stackformer
Version: 0.1.6
Summary: Modular transformer blocks built in PyTorch
Author-email: Gurumurthy <gurumurthy.00300@gmail.com>
License-Expression: MIT
Project-URL: Repository, https://github.com/Gurumurthy30/Stackformer
Project-URL: Issue Tracker, https://github.com/Gurumurthy30/Stackformer/issues
Project-URL: Discussions, https://github.com/Gurumurthy30/Stackformer/discussions
Classifier: Programming Language :: Python :: 3
Classifier: Operating System :: OS Independent
Classifier: Topic :: Scientific/Engineering :: Artificial Intelligence
Classifier: Topic :: Software Development :: Libraries :: Python Modules
Requires-Python: >=3.9
License-File: LICENSE
Requires-Dist: torch<2.7,>=2.0
Requires-Dist: tqdm<5.0,>=4.5
Dynamic: license-file
